{
  "name": "tawana-action",
  "private": true,
  "version": "1.0.0",
  "description": "",
  "type": "module",
  "main": "index.js",
  "scripts": {
    "dev": "vite",
    "build": "vite build",
    "preview": "vite preview",
    "test": "vitest run --passWithNoTests"
  },
  "repository": {
    "type": "git",
    "url": "git+https://github.com/slemont68/tawana-gh-actions.git"
  },
  "keywords": [],
  "author": "",
  "license": "ISC",
  "bugs": {
    "url": "https://github.com/slemont68/tawana-gh-actions/issues"
  },
  "homepage": "https://github.com/slemont68/tawana-gh-actions#readme",
  "dependencies": {
    "react": "^18.2.0",
    "react-dom": "^18.2.0"
  },
  "devDependencies": {
    "@testing-library/jest-dom": "^5.16.5",
    "@testing-library/react": "^13.3.0",
    "@testing-library/user-event": "^14.4.3",
    "@types/react": "^18.0.17",
    "@types/react-dom": "^18.0.6",
    "@vitejs/plugin-react": "^6.0.2",
    "jsdom": "^29.1.1",
    "vite": "^8.0.13",
    "vitest": "^4.1.6"
  }
}
